<core:FragmentDefinition xmlns="sap.m" xmlns:f="sap.ui.layout.form" xmlns:l="sap.ui.layout" xmlns:core="sap.ui.core" id="inputdialog">
	<Dialog showHeader="false">
		<Panel>
			<headerToolbar>
				<OverflowToolbar height="3rem" class="Panel_header">
					<Title text="Add E-Way Bill Distance" class="labelselectrep"/>
					<ToolbarSpacer/>
					<Button icon="sap-icon://decline" press="onCancel"></Button>
				</OverflowToolbar>
			</headerToolbar>
			<f:SimpleForm id="SimpleFormDilay82" editable="true" layout="ResponsiveGridLayout" title="" labelSpanXL="3" labelSpanL="3" labelSpanM="3"
				labelSpanS="12" adjustLabelSpan="false" emptySpanXL="4" emptySpanL="4" emptySpanM="4" emptySpanS="0" columnsXL="1" columnsL="1" columnsM="1"
				singleContainerFullSize="false">
				<f:content>
					<Label text="Seller Code" required="true"/>
					<Input id="sellerCode" maxLength="10"/>
					<Label text="Buyer Code" required="true"/>
					<Input id="buyerCode" maxLength="10"/>
					<Label text="Distance"/>
					<Input id="distance" type="Number" maxLength="6"/>
					<Label text="Active/Deactive"/>
					<CheckBox id="activedeactiveewd"></CheckBox>
				</f:content>
			</f:SimpleForm>
		</Panel>
		<buttons>
			<Button text="Create" type="Emphasized" press="oncreate"/>
			<Button text="Clear" type="Emphasized" press="onclear"/>
		</buttons>
	</Dialog>
</core:FragmentDefinition>